explainable_attention/__init__.py
explainable_attention/layers.py
explainable_attention/utils.py
explainable_attention/self_attention_attribution/__init__.py
explainable_attention/self_attention_attribution/layers.py
explainable_attention-0.0.2.dist-info/METADATA
explainable_attention-0.0.2.dist-info/WHEEL
explainable_attention-0.0.2.dist-info/top_level.txt
explainable_attention-0.0.2.dist-info/RECORD
