Metadata-Version: 2.4
Name: explainable-attention
Version: 0.0.2
Summary: Implementation of various tools for multi-head attention explainability from transformers.
Author-email: "David W. Ludwig II" <davidludwigii@gmail.com>
Project-URL: Homepage, https://github.com/DLii-Research/explainable-attention
Project-URL: Bug Tracker, https://github.com/DLii-Research/explainable-attention/issues
Requires-Python: >=3.8
Requires-Dist: attn-gym
Requires-Dist: torch>=2.5.0
